stackerd_game/__init__.py
stackerd_game/assets.py
stackerd_game/audio.py
stackerd_game/core.py
stackerd_game/events.py
stackerd_game/graphics.py
stackerd_game/input.py
stackerd_game-0.1.0.dist-info/METADATA
stackerd_game-0.1.0.dist-info/WHEEL
stackerd_game-0.1.0.dist-info/top_level.txt
stackerd_game-0.1.0.dist-info/RECORD
