Metadata-Version: 2.1
Name: stackerd-game
Version: 0.1.0
Summary: An alternative to Pygame for game development
Author: Your Name
Author-email: your.email@example.com
Requires-Python: >=3.6
